bia_explorer/__init__.py
bia_explorer/api.py
bia_explorer/biostudies.py
bia_explorer/io.py
bia_explorer/models.py
bia_explorer/utils.py
bia_explorer-0.1.5.dist-info/WHEEL
bia_explorer-0.1.5.dist-info/METADATA
bia_explorer-0.1.5.dist-info/RECORD
