Metadata-Version: 2.1
Name: bia-explorer
Version: 0.1.5
Summary: 
License: MIT
Author: Matthew Hartley
Author-email: matthewh@ebi.ac.uk
Requires-Python: >=3.9,<4.0
Classifier: License :: OSI Approved :: MIT License
Classifier: Programming Language :: Python :: 3
Classifier: Programming Language :: Python :: 3.9
Classifier: Programming Language :: Python :: 3.10
Classifier: Programming Language :: Python :: 3.11
Requires-Dist: Pillow (>=9.3.0,<10.0.0)
Requires-Dist: aiobotocore (>=2.0.0,<3.0.0)
Requires-Dist: bia-integrator-api (>=0.3.0,<0.4.0)
Requires-Dist: dask (>=2024.4.1,<2025.0.0)
Requires-Dist: jupyter (>=1.0.0,<2.0.0)
Requires-Dist: ome-zarr (>=0.8.3,<0.9.0)
Requires-Dist: pydantic (>=1.10.2,<2.0.0)
Requires-Dist: requests (>=2.28.1,<3.0.0)
Requires-Dist: zarr (>=2.17.2,<3.0.0)
